Metadata-Version: 2.1
Name: dfwx-openchat
Version: 1.0.4
Summary: A package for dfwx_openchat.
Home-page: UNKNOWN
Author: DavidTaylor1987
Author-email: domainseller@foxmail.com
License: Apache License 2.0
Platform: UNKNOWN
